{"nodes":[{"label":"A20","style":"internal"},{"label":"Apoptosis","style":"internal"},{"label":"BID","style":"internal"},{"label":"BclxL","style":"internal"},{"label":"CD45","style":"external"},{"label":"CREB","style":"internal"},{"label":"CTLA4","style":"internal"},{"label":"Caspase","style":"internal"},{"label":"Ceramide","style":"internal"},{"label":"Cytoskeleton_signaling","style":"internal"},{"label":"DISC","style":"internal"},{"label":"ERK","style":"internal"},{"label":"FLIP","style":"internal"},{"label":"FYN","style":"internal"},{"label":"Fas","style":"internal"},{"label":"FasL","style":"internal"},{"label":"FasT","style":"internal"},{"label":"GAP","style":"internal"},{"label":"GPCR","style":"internal"},{"label":"GRB2","style":"internal"},{"label":"GZMB","style":"internal"},{"label":"IAP","style":"internal"},{"label":"IFN","style":"external"},{"label":"IFNG","style":"internal"},{"label":"IFNGT","style":"internal"},{"label":"IL15","style":"external"},{"label":"IL2","style":"internal"},{"label":"IL2RA","style":"internal"},{"label":"IL2RAT","style":"internal"},{"label":"IL2RB","style":"internal"},{"label":"IL2RBT","style":"internal"},{"label":"JAK","style":"internal"},{"label":"LCK","style":"internal"},{"label":"MCL1","style":"internal"},{"label":"MEK","style":"internal"},{"label":"NFAT","style":"internal"},{"label":"NFKB","style":"internal"},{"label":"P2","style":"internal"},{"label":"P27","style":"internal"},{"label":"PDGF","style":"external"},{"label":"PDGFR","style":"internal"},{"label":"PI3K","style":"internal"},{"label":"PLCG1","style":"internal"},{"label":"Proliferation","style":"internal"},{"label":"RANTES","style":"internal"},{"label":"RAS","style":"internal"},{"label":"S1P","style":"internal"},{"label":"SMAD","style":"internal"},{"label":"SOCS","style":"internal"},{"label":"SPHK1","style":"internal"},{"label":"STAT3","style":"internal"},{"label":"Stimuli","style":"external"},{"label":"Stimuli2","style":"external"},{"label":"TAX","style":"external"},{"label":"TBET","style":"internal"},{"label":"TCR","style":"internal"},{"label":"TNF","style":"internal"},{"label":"TPL2","style":"internal"},{"label":"TRADD","style":"internal"},{"label":"ZAP70","style":"internal"},{"label":"sFas","style":"internal"}],"edges":[{"source":0,"target":58},{"source":1,"target":0},{"source":1,"target":1},{"source":1,"target":2},{"source":1,"target":3},{"source":1,"target":5},{"source":1,"target":6},{"source":1,"target":7},{"source":1,"target":8},{"source":1,"target":9},{"source":1,"target":10},{"source":1,"target":11},{"source":1,"target":12},{"source":1,"target":13},{"source":1,"target":14},{"source":1,"target":15},{"source":1,"target":16},{"source":1,"target":17},{"source":1,"target":18},{"source":1,"target":19},{"source":1,"target":20},{"source":1,"target":21},{"source":1,"target":23},{"source":1,"target":24},{"source":1,"target":26},{"source":1,"target":27},{"source":1,"target":28},{"source":1,"target":29},{"source":1,"target":30},{"source":1,"target":31},{"source":1,"target":32},{"source":1,"target":33},{"source":1,"target":34},{"source":1,"target":35},{"source":1,"target":36},{"source":1,"target":37},{"source":1,"target":38},{"source":1,"target":40},{"source":1,"target":41},{"source":1,"target":42},{"source":1,"target":43},{"source":1,"target":44},{"source":1,"target":45},{"source":1,"target":46},{"source":1,"target":47},{"source":1,"target":48},{"source":1,"target":49},{"source":1,"target":50},{"source":1,"target":54},{"source":1,"target":55},{"source":1,"target":56},{"source":1,"target":57},{"source":1,"target":58},{"source":1,"target":59},{"source":1,"target":60},{"source":2,"target":3},{"source":2,"target":7},{"source":2,"target":7},{"source":2,"target":21},{"source":3,"target":2},{"source":4,"target":31},{"source":4,"target":32},{"source":5,"target":12},{"source":5,"target":20},{"source":6,"target":55},{"source":7,"target":1},{"source":7,"target":2},{"source":8,"target":10},{"source":8,"target":46},{"source":10,"target":3},{"source":10,"target":7},{"source":10,"target":12},{"source":11,"target":5},{"source":11,"target":15},{"source":11,"target":30},{"source":12,"target":10},{"source":12,"target":36},{"source":13,"target":9},{"source":13,"target":59},{"source":14,"target":8},{"source":14,"target":10},{"source":14,"target":10},{"source":15,"target":14},{"source":16,"target":10},{"source":16,"target":14},{"source":16,"target":60},{"source":17,"target":17},{"source":17,"target":45},{"source":18,"target":47},{"source":19,"target":42},{"source":19,"target":45},{"source":20,"target":2},{"source":20,"target":3},{"source":20,"target":7},{"source":21,"target":7},{"source":21,"target":36},{"source":21,"target":58},{"source":22,"target":5},{"source":23,"target":12},{"source":23,"target":20},{"source":23,"target":31},{"source":23,"target":37},{"source":24,"target":23},{"source":24,"target":23},{"source":24,"target":23},{"source":25,"target":17},{"source":25,"target":23},{"source":25,"target":29},{"source":25,"target":48},{"source":26,"target":10},{"source":26,"target":17},{"source":26,"target":23},{"source":26,"target":27},{"source":26,"target":28},{"source":26,"target":29},{"source":27,"target":27},{"source":27,"target":31},{"source":28,"target":27},{"source":29,"target":13},{"source":29,"target":19},{"source":29,"target":31},{"source":29,"target":32},{"source":29,"target":33},{"source":30,"target":29},{"source":26,"target":48},{"source":31,"target":48},{"source":31,"target":50},{"source":31,"target":54},{"source":32,"target":59},{"source":33,"target":2},{"source":34,"target":11},{"source":35,"target":15},{"source":35,"target":24},{"source":35,"target":26},{"source":36,"target":0},{"source":36,"target":3},{"source":36,"target":12},{"source":36,"target":15},{"source":36,"target":16},{"source":36,"target":21},{"source":36,"target":26},{"source":36,"target":28},{"source":36,"target":33},{"source":36,"target":44},{"source":36,"target":56},{"source":38,"target":43},{"source":37,"target":23},{"source":37,"target":37},{"source":39,"target":40},{"source":40,"target":17},{"source":40,"target":41},{"source":40,"target":42},{"source":40,"target":45},{"source":40,"target":49},{"source":41,"target":11},{"source":41,"target":33},{"source":41,"target":35},{"source":41,"target":36},{"source":41,"target":57},{"source":44,"target":31},{"source":45,"target":17},{"source":45,"target":34},{"source":45,"target":41},{"source":46,"target":8},{"source":46,"target":18},{"source":46,"target":40},{"source":47,"target":23},{"source":48,"target":31},{"source":49,"target":46},{"source":50,"target":3},{"source":50,"target":15},{"source":50,"target":24},{"source":50,"target":26},{"source":50,"target":28},{"source":50,"target":33},{"source":50,"target":38},{"source":50,"target":43},{"source":52,"target":37},{"source":51,"target":23},{"source":51,"target":55},{"source":53,"target":57},{"source":54,"target":20},{"source":54,"target":24},{"source":54,"target":26},{"source":54,"target":30},{"source":54,"target":54},{"source":55,"target":6},{"source":55,"target":13},{"source":55,"target":32},{"source":56,"target":57},{"source":56,"target":58},{"source":57,"target":36},{"source":58,"target":7},{"source":58,"target":36},{"source":59,"target":19},{"source":59,"target":32},{"source":60,"target":14}]}